aquama_hydro_client/__init__.py
aquama_hydro_client/access.py
aquama_hydro_client/aquama_hydro.py
aquama_hydro_client/aquama_machine.py
aquama_hydro_client/exceptions.py
aquama_hydro_client/message.py
aquama_hydro_client/serial_number.py
aquama_hydro_client-0.3.2.dist-info/WHEEL
aquama_hydro_client-0.3.2.dist-info/METADATA
aquama_hydro_client-0.3.2.dist-info/RECORD
