Metadata-Version: 2.1
Name: aquama-hydro-client
Version: 0.3.2
Summary: 
Author: Sébastien Gendre
Author-email: sgendre@aquama.com
Requires-Python: >=3.7,<4.0
Classifier: Programming Language :: Python :: 3
Classifier: Programming Language :: Python :: 3.10
Classifier: Programming Language :: Python :: 3.7
Classifier: Programming Language :: Python :: 3.8
Classifier: Programming Language :: Python :: 3.9
Requires-Dist: requests (>=2.25.1,<3.0.0)
